./.gitignore
./PKG-INFO
./README.md
./letta_memory.py
./prompt_formatter.py
./pyproject.toml
./schemas.py
./uv.lock
./examples/chat.py
./examples/chat_with_compaction.py
./tests/test_documentation.py
./tests/test_messages.py
./tests/test_messages_old.py
./tests/test_subconscious_agent.py
./tests/data/documentation/python_reference.md
letta_memory-0.1.5.dist-info/METADATA
letta_memory-0.1.5.dist-info/WHEEL
letta_memory-0.1.5.dist-info/RECORD
