Metadata-Version: 2.4
Name: letta-memory
Version: 0.1.5
Summary: An experimental SDK for using Letta subagents for pluggable memory management
Project-URL: Homepage, https://github.com/letta-ai/letta-memory
Project-URL: Repository, https://github.com/letta-ai/letta-memory
Author-email: Sarah Wooders <sarah@example.com>
License-Expression: MIT
Classifier: Development Status :: 3 - Alpha
Classifier: Intended Audience :: Developers
Classifier: License :: OSI Approved :: MIT License
Classifier: Programming Language :: Python :: 3
Classifier: Programming Language :: Python :: 3.8
Classifier: Programming Language :: Python :: 3.9
Classifier: Programming Language :: Python :: 3.10
Classifier: Programming Language :: Python :: 3.11
Requires-Python: >=3.8
Requires-Dist: letta-client==0.1.307
Requires-Dist: openai>=1.102.0
Requires-Dist: pydantic>=2.0.0
Requires-Dist: pytest>=8.3.5
Provides-Extra: dev
Requires-Dist: black; extra == 'dev'
Requires-Dist: isort; extra == 'dev'
Requires-Dist: mypy; extra == 'dev'
Requires-Dist: pytest-asyncio; extra == 'dev'
Requires-Dist: pytest>=7.0; extra == 'dev'
